sprinkle/__init__.py
sprinkle/_version.py
sprinkle-0.0.1.dist-info/METADATA
sprinkle-0.0.1.dist-info/WHEEL
sprinkle-0.0.1.dist-info/top_level.txt
sprinkle-0.0.1.dist-info/RECORD
