Metadata-Version: 2.1
Name: sprinkle
Version: 0.0.1
Summary: Sprinkle: Synapse Pipeline for Research Integration, Number Krunching, Loving Experiments.
Home-page: https://github.com/LemonJust/sprinkle
Author: Anna Nadtochiy
Author-email: lemonjustgithub@gmail.com
License: BSD-3-Clause
Project-URL: Bug Tracker, https://github.com/LemonJust/sprinkle/issues
Project-URL: Documentation, https://github.com/LemonJust/sprinkle#README.md
Project-URL: Source Code, https://github.com/LemonJust/sprinkle
Project-URL: User Support, https://github.com/LemonJust/sprinkle/issues
Classifier: Development Status :: 3 - Alpha
Classifier: Intended Audience :: Science/Research
Classifier: License :: OSI Approved :: BSD License
Classifier: Operating System :: OS Independent
Classifier: Programming Language :: Python
Classifier: Programming Language :: Python :: 3
Classifier: Programming Language :: Python :: 3 :: Only
Classifier: Programming Language :: Python :: 3.8
Classifier: Programming Language :: Python :: 3.9
Classifier: Programming Language :: Python :: 3.10
Classifier: Topic :: Scientific/Engineering :: Image Processing
Requires-Python: >=3.8
Requires-Dist: numpy
Requires-Dist: tifffile
Provides-Extra: testing
Requires-Dist: tox ; extra == 'testing'
Requires-Dist: pytest ; extra == 'testing'
Requires-Dist: pytest-cov ; extra == 'testing'
